bitaxetool/__init__.py
bitaxetool/__main__.py
bitaxetool/bitaxetool.py
bitaxetool/nvs_partition_gen.py
bitaxetool/validation.py
bitaxetool-0.6.1.dist-info/licenses/LICENSE
bitaxetool-0.6.1.dist-info/METADATA
bitaxetool-0.6.1.dist-info/WHEEL
bitaxetool-0.6.1.dist-info/entry_points.txt
bitaxetool-0.6.1.dist-info/top_level.txt
bitaxetool-0.6.1.dist-info/RECORD
