Metadata-Version: 2.4
Name: bitaxetool
Version: 0.6.1
Summary: Firmware and configuration tool for Bitaxe
Author-email: johnny9 <johnny9dev@pm.me>
Project-URL: homepage, https://github.com/johnny9/bitaxetool
Requires-Python: >=3
License-File: LICENSE
Requires-Dist: esptool==4.9.0
Provides-Extra: validate
Requires-Dist: cerberus==1.3.4; extra == "validate"
Dynamic: license-file
